fullvision_demo/output/aig/simple_alu_gtech.v
/* Generated by Yosys 0.33 (git sha1 2584903a060) */

module simple_alu(clk, rst_n, a, b, op, result, zero, carry, add_result, sub_result, and_result, or_result, xor_result, add_carry, result_is_zero);
  wire _000_;
  wire _001_;
  wire _002_;
  wire _003_;
  wire _004_;
  wire _005_;
  wire _006_;
  wire _007_;
  wire [3:0] _008_;
  wire [1:0] _009_;
  wire _010_;
  wire _011_;
  wire _012_;
  wire _013_;
  wire _014_;
  wire _015_;
  wire [8:0] _016_;
  wire [8:0] _017_;
  wire [8:0] _018_;
  wire [8:0] _019_;
  wire [8:0] _020_;
  wire _021_;
  wire _022_;
  wire _023_;
  wire _024_;
  wire _025_;
  wire _026_;
  wire _027_;
  wire _028_;
  wire _029_;
  wire _030_;
  wire _031_;
  wire _032_;
  wire _033_;
  wire _034_;
  wire _035_;
  wire _036_;
  wire _037_;
  wire _038_;
  wire _039_;
  wire _040_;
  wire _041_;
  wire _042_;
  wire _043_;
  wire _044_;
  wire _045_;
  wire _046_;
  wire _047_;
  wire _048_;
  wire _049_;
  wire _050_;
  wire _051_;
  wire [7:0] _052_;
  wire [7:0] _053_;
  wire [7:0] _054_;
  wire [7:0] _055_;
  input [7:0] a;
  wire [7:0] a;
  output add_carry;
  wire add_carry;
  wire [8:0] add_full;
  output [7:0] add_result;
  wire [7:0] add_result;
  output [7:0] and_result;
  wire [7:0] and_result;
  input [7:0] b;
  wire [7:0] b;
  output carry;
  reg carry;
  input clk;
  wire clk;
  input [2:0] op;
  wire [2:0] op;
  output [7:0] or_result;
  wire [7:0] or_result;
  output [7:0] result;
  reg [7:0] result;
  output result_is_zero;
  wire result_is_zero;
  input rst_n;
  wire rst_n;
  wire [7:0] selected_result;
  wire [8:0] sub_full;
  output [7:0] sub_result;
  wire [7:0] sub_result;
  output [7:0] xor_result;
  wire [7:0] xor_result;
  output zero;
  reg zero;
  always @(posedge clk, negedge rst_n)
    if (!rst_n) result[0] <= 1'h0;
    else result[0] <= selected_result[0];
  always @(posedge clk, negedge rst_n)
    if (!rst_n) result[1] <= 1'h0;
    else result[1] <= selected_result[1];
  always @(posedge clk, negedge rst_n)
    if (!rst_n) result[2] <= 1'h0;
    else result[2] <= selected_result[2];
  always @(posedge clk, negedge rst_n)
    if (!rst_n) result[3] <= 1'h0;
    else result[3] <= selected_result[3];
  always @(posedge clk, negedge rst_n)
    if (!rst_n) result[4] <= 1'h0;
    else result[4] <= selected_result[4];
  always @(posedge clk, negedge rst_n)
    if (!rst_n) result[5] <= 1'h0;
    else result[5] <= selected_result[5];
  always @(posedge clk, negedge rst_n)
    if (!rst_n) result[6] <= 1'h0;
    else result[6] <= selected_result[6];
  always @(posedge clk, negedge rst_n)
    if (!rst_n) result[7] <= 1'h0;
    else result[7] <= selected_result[7];
  always @(posedge clk, negedge rst_n)
    if (!rst_n) zero <= 1'h0;
    else zero <= result_is_zero;
  always @(posedge clk, negedge rst_n)
    if (!rst_n) carry <= 1'h0;
    else carry <= _000_;
  assign _001_ = ~op[2];
  assign _002_ = ~op[0];
  assign _003_ = ~op[1];
  assign sub_full[0] = ~_019_[0];
  assign _004_ = _002_ | op[1];
  assign _012_ = _004_ | op[2];
  assign _005_ = op[0] | _003_;
  assign _013_ = _005_ | op[2];
  assign _006_ = _002_ | _003_;
  assign _014_ = _006_ | op[2];
  assign _015_ = _007_ | _001_;
  assign _008_[0] = selected_result[0] | selected_result[1];
  assign _008_[1] = selected_result[2] | selected_result[3];
  assign _008_[2] = selected_result[4] | selected_result[5];
  assign _008_[3] = selected_result[6] | selected_result[7];
  assign _009_[0] = _008_[0] | _008_[1];
  assign _009_[1] = _008_[2] | _008_[3];
  assign _010_ = _009_[0] | _009_[1];
  assign _007_ = op[0] | op[1];
  assign _011_ = _007_ | op[2];
  assign result_is_zero = ~_010_;
  assign _055_[0] = _015_ ? 1'h0 : xor_result[0];
  assign _055_[1] = _015_ ? 1'h0 : xor_result[1];
  assign _055_[2] = _015_ ? 1'h0 : xor_result[2];
  assign _055_[3] = _015_ ? 1'h0 : xor_result[3];
  assign _055_[4] = _015_ ? 1'h0 : xor_result[4];
  assign _055_[5] = _015_ ? 1'h0 : xor_result[5];
  assign _055_[6] = _015_ ? 1'h0 : xor_result[6];
  assign _055_[7] = _015_ ? 1'h0 : xor_result[7];
  assign _054_[0] = _014_ ? _055_[0] : or_result[0];
  assign _054_[1] = _014_ ? _055_[1] : or_result[1];
  assign _054_[2] = _014_ ? _055_[2] : or_result[2];
  assign _054_[3] = _014_ ? _055_[3] : or_result[3];
  assign _054_[4] = _014_ ? _055_[4] : or_result[4];
  assign _054_[5] = _014_ ? _055_[5] : or_result[5];
  assign _054_[6] = _014_ ? _055_[6] : or_result[6];
  assign _054_[7] = _014_ ? _055_[7] : or_result[7];
  assign _053_[0] = _013_ ? _054_[0] : and_result[0];
  assign _053_[1] = _013_ ? _054_[1] : and_result[1];
  assign _053_[2] = _013_ ? _054_[2] : and_result[2];
  assign _053_[3] = _013_ ? _054_[3] : and_result[3];
  assign _053_[4] = _013_ ? _054_[4] : and_result[4];
  assign _053_[5] = _013_ ? _054_[5] : and_result[5];
  assign _053_[6] = _013_ ? _054_[6] : and_result[6];
  assign _053_[7] = _013_ ? _054_[7] : and_result[7];
  assign _052_[0] = _012_ ? _053_[0] : sub_full[0];
  assign _052_[1] = _012_ ? _053_[1] : sub_full[1];
  assign _052_[2] = _012_ ? _053_[2] : sub_full[2];
  assign _052_[3] = _012_ ? _053_[3] : sub_full[3];
  assign _052_[4] = _012_ ? _053_[4] : sub_full[4];
  assign _052_[5] = _012_ ? _053_[5] : sub_full[5];
  assign _052_[6] = _012_ ? _053_[6] : sub_full[6];
  assign _052_[7] = _012_ ? _053_[7] : sub_full[7];
  assign selected_result[0] = _011_ ? _052_[0] : xor_result[0];
  assign selected_result[1] = _011_ ? _052_[1] : add_full[1];
  assign selected_result[2] = _011_ ? _052_[2] : add_full[2];
  assign selected_result[3] = _011_ ? _052_[3] : add_full[3];
  assign selected_result[4] = _011_ ? _052_[4] : add_full[4];
  assign selected_result[5] = _011_ ? _052_[5] : add_full[5];
  assign selected_result[6] = _011_ ? _052_[6] : add_full[6];
  assign selected_result[7] = _011_ ? _052_[7] : add_full[7];
  assign _000_ = _011_ ? 1'h0 : add_carry;
  assign _017_[0] = ~b[0];
  assign _017_[1] = ~b[1];
  assign _017_[2] = ~b[2];
  assign _017_[3] = ~b[3];
  assign _017_[4] = ~b[4];
  assign _017_[5] = ~b[5];
  assign _017_[6] = ~b[6];
  assign _017_[7] = ~b[7];
  assign or_result[0] = a[0] | b[0];
  assign or_result[1] = a[1] | b[1];
  assign or_result[2] = a[2] | b[2];
  assign or_result[3] = a[3] | b[3];
  assign or_result[4] = a[4] | b[4];
  assign or_result[5] = a[5] | b[5];
  assign or_result[6] = a[6] | b[6];
  assign or_result[7] = a[7] | b[7];
  assign add_full[1] = xor_result[1] ^ and_result[0];
  assign add_full[2] = xor_result[2] ^ _016_[1];
  assign add_full[3] = xor_result[3] ^ _016_[2];
  assign add_full[4] = xor_result[4] ^ _016_[3];
  assign add_full[5] = xor_result[5] ^ _016_[4];
  assign add_full[6] = xor_result[6] ^ _016_[5];
  assign add_full[7] = xor_result[7] ^ _016_[6];
  assign xor_result[0] = b[0] ^ a[0];
  assign xor_result[1] = b[1] ^ a[1];
  assign xor_result[2] = b[2] ^ a[2];
  assign xor_result[3] = b[3] ^ a[3];
  assign xor_result[4] = b[4] ^ a[4];
  assign xor_result[5] = b[5] ^ a[5];
  assign xor_result[6] = b[6] ^ a[6];
  assign xor_result[7] = b[7] ^ a[7];
  assign and_result[0] = b[0] & a[0];
  assign and_result[1] = b[1] & a[1];
  assign and_result[2] = b[2] & a[2];
  assign and_result[3] = b[3] & a[3];
  assign and_result[4] = b[4] & a[4];
  assign and_result[5] = b[5] & a[5];
  assign and_result[6] = b[6] & a[6];
  assign and_result[7] = b[7] & a[7];
  assign sub_full[1] = _019_[1] ^ _018_[0];
  assign sub_full[2] = _019_[2] ^ _018_[1];
  assign sub_full[3] = _019_[3] ^ _018_[2];
  assign sub_full[4] = _019_[4] ^ _018_[3];
  assign sub_full[5] = _019_[5] ^ _018_[4];
  assign sub_full[6] = _019_[6] ^ _018_[5];
  assign sub_full[7] = _019_[7] ^ _018_[6];
  assign _019_[0] = a[0] ^ _017_[0];
  assign _019_[1] = a[1] ^ _017_[1];
  assign _019_[2] = a[2] ^ _017_[2];
  assign _019_[3] = a[3] ^ _017_[3];
  assign _019_[4] = a[4] ^ _017_[4];
  assign _019_[5] = a[5] ^ _017_[5];
  assign _019_[6] = a[6] ^ _017_[6];
  assign _019_[7] = a[7] ^ _017_[7];
  assign _020_[0] = a[0] & _017_[0];
  assign _020_[1] = a[1] & _017_[1];
  assign _020_[2] = a[2] & _017_[2];
  assign _020_[3] = a[3] & _017_[3];
  assign _020_[4] = a[4] & _017_[4];
  assign _020_[5] = a[5] & _017_[5];
  assign _020_[6] = a[6] & _017_[6];
  assign _021_ = xor_result[1] & and_result[0];
  assign _022_ = xor_result[3] & and_result[2];
  assign _023_ = xor_result[5] & and_result[4];
  assign _024_ = xor_result[7] & and_result[6];
  assign _025_ = _028_ & _016_[1];
  assign _026_ = _030_ & _037_;
  assign _027_ = _031_ & _016_[3];
  assign _028_ = xor_result[3] & xor_result[2];
  assign _029_ = xor_result[5] & xor_result[4];
  assign _030_ = xor_result[7] & xor_result[6];
  assign _031_ = _030_ & _029_;
  assign _032_ = _029_ & _016_[3];
  assign _033_ = xor_result[2] & _016_[1];
  assign _034_ = xor_result[4] & _016_[3];
  assign _035_ = xor_result[6] & _016_[5];
  assign _016_[1] = and_result[1] | _021_;
  assign _036_ = and_result[3] | _022_;
  assign _037_ = and_result[5] | _023_;
  assign _038_ = and_result[7] | _024_;
  assign _016_[3] = _036_ | _025_;
  assign _039_ = _038_ | _026_;
  assign add_carry = _039_ | _027_;
  assign _016_[5] = _037_ | _032_;
  assign _016_[2] = and_result[2] | _033_;
  assign _016_[4] = and_result[4] | _034_;
  assign _016_[6] = and_result[6] | _035_;
  assign _040_ = _019_[1] & _018_[0];
  assign _041_ = _019_[3] & _020_[2];
  assign _042_ = _019_[5] & _020_[4];
  assign _043_ = _044_ & _018_[1];
  assign _044_ = _019_[3] & _019_[2];
  assign _045_ = _019_[5] & _019_[4];
  assign _046_ = _045_ & _018_[3];
  assign _047_ = _019_[2] & _018_[1];
  assign _048_ = _019_[4] & _018_[3];
  assign _049_ = _019_[6] & _018_[5];
  assign _018_[0] = _020_[0] | _019_[0];
  assign _018_[1] = _020_[1] | _040_;
  assign _050_ = _020_[3] | _041_;
  assign _051_ = _020_[5] | _042_;
  assign _018_[3] = _050_ | _043_;
  assign _018_[5] = _051_ | _046_;
  assign _018_[2] = _020_[2] | _047_;
  assign _018_[4] = _020_[4] | _048_;
  assign _018_[6] = _020_[6] | _049_;
  assign { _016_[8:7], _016_[0] } = { 1'h0, add_carry, and_result[0] };
  assign _017_[8] = 1'h1;
  assign _018_[7] = _018_[8];
  assign _019_[8] = 1'h1;
  assign _020_[8] = 1'h0;
  assign { add_full[8], add_full[0] } = { add_carry, xor_result[0] };
  assign add_result = { add_full[7:1], xor_result[0] };
  assign sub_result = sub_full[7:0];
endmodule

fullvision_demo/designs/simple_alu/testbench.v
/**
 * Testbench for Simple ALU
 */

`timescale 1ns/1ps

module testbench;

    reg        clk;
    reg        rst_n;
    reg  [7:0] a;
    reg  [7:0] b;
    reg  [2:0] op;

    // 主输出
    wire [7:0] result;
    wire       zero;
    wire       carry;

    // 中间信号输出
    wire [7:0] add_result;
    wire [7:0] sub_result;
    wire [7:0] and_result;
    wire [7:0] or_result;
    wire [7:0] xor_result;
    wire       add_carry;
    wire       result_is_zero;

    // 实例化DUT
    simple_alu dut (
        .clk(clk),
        .rst_n(rst_n),
        .a(a),
        .b(b),
        .op(op),
        .result(result),
        .zero(zero),
        .carry(carry),
        .add_result(add_result),
        .sub_result(sub_result),
        .and_result(and_result),
        .or_result(or_result),
        .xor_result(xor_result),
        .add_carry(add_carry),
        .result_is_zero(result_is_zero)
    );

    // 时钟生成
    initial begin
        clk = 0;
        forever #5 clk = ~clk;
    end

    // VCD波形输出
    initial begin
`ifdef GOLDEN_VCD
        $dumpfile(`GOLDEN_VCD_FILE);
`else
        $dumpfile("simple_alu.vcd");
`endif
        $dumpvars(0, testbench);
    end

`ifdef TRACE_SIGNAL_LIST
    initial begin
        $trace_init(`TRACE_SIGNAL_LIST, "testbench.clk", `TRACE_OUTPUT_FILE);
    end
`endif

    // 测试序列
    initial begin
        // 初始化
        rst_n = 0;
        a = 8'h00;
        b = 8'h00;
        op = 3'b000;

        // 复位
        #20;
        rst_n = 1;

        // 测试ADD操作
        #10;
        a = 8'h05;
        b = 8'h03;
        op = 3'b000;  // ADD: 5 + 3 = 8

        #10;
        a = 8'hFF;
        b = 8'h01;
        op = 3'b000;  // ADD: 255 + 1 = 0 (with carry)

        #10;
        a = 8'h7F;
        b = 8'h01;
        op = 3'b000;  // ADD: 127 + 1 = 128

        // 测试SUB操作
        #10;
        a = 8'h10;
        b = 8'h05;
        op = 3'b001;  // SUB: 16 - 5 = 11

        #10;
        a = 8'h05;
        b = 8'h10;
        op = 3'b001;  // SUB: 5 - 16 = 245 (wrap around)

        // 测试AND操作
        #10;
        a = 8'hAA;
        b = 8'h55;
        op = 3'b010;  // AND: 0xAA & 0x55 = 0x00

        #10;
        a = 8'hFF;
        b = 8'h0F;
        op = 3'b010;  // AND: 0xFF & 0x0F = 0x0F

        // 测试OR操作
        #10;
        a = 8'hAA;
        b = 8'h55;
        op = 3'b011;  // OR: 0xAA | 0x55 = 0xFF

        // 测试XOR操作
        #10;
        a = 8'hAA;
        b = 8'hAA;
        op = 3'b100;  // XOR: 0xAA ^ 0xAA = 0x00

        #10;
        a = 8'hAA;
        b = 8'h55;
        op = 3'b100;  // XOR: 0xAA ^ 0x55 = 0xFF

        // 测试零检测
        #10;
        a = 8'h00;
        b = 8'h00;
        op = 3'b000;  // ADD: 0 + 0 = 0 (zero flag)

        // 结束
        #50;
        $finish;
    end

endmodule

fullvision_demo/output/simple_alu.vcd
$date
	Thu Dec 25 11:17:41 2025
$end
$version
	Icarus Verilog
$end
$timescale
	1ps
$end
$scope module testbench $end
$var wire 1 ! zero $end
$var wire 8 " xor_result [7:0] $end
$var wire 8 # sub_result [7:0] $end
$var wire 1 $ result_is_zero $end
$var wire 8 % result [7:0] $end
$var wire 8 & or_result [7:0] $end
$var wire 1 ' carry $end
$var wire 8 ( and_result [7:0] $end
$var wire 8 ) add_result [7:0] $end
$var wire 1 * add_carry $end
$var reg 8 + a [7:0] $end
$var reg 8 , b [7:0] $end
$var reg 1 - clk $end
$var reg 3 . op [2:0] $end
$var reg 1 / rst_n $end
$scope module dut $end
$var wire 1 0 _001_ $end
$var wire 1 1 _002_ $end
$var wire 1 2 _003_ $end
$var wire 1 3 _004_ $end
$var wire 1 4 _005_ $end
$var wire 1 5 _006_ $end
$var wire 1 6 _007_ $end
$var wire 1 7 _010_ $end
$var wire 1 8 _011_ $end
$var wire 1 9 _012_ $end
$var wire 1 : _013_ $end
$var wire 1 ; _014_ $end
$var wire 1 < _015_ $end
$var wire 1 = _021_ $end
$var wire 1 > _022_ $end
$var wire 1 ? _023_ $end
$var wire 1 @ _024_ $end
$var wire 1 A _025_ $end
$var wire 1 B _026_ $end
$var wire 1 C _027_ $end
$var wire 1 D _028_ $end
$var wire 1 E _029_ $end
$var wire 1 F _030_ $end
$var wire 1 G _031_ $end
$var wire 1 H _032_ $end
$var wire 1 I _033_ $end
$var wire 1 J _034_ $end
$var wire 1 K _035_ $end
$var wire 1 L _036_ $end
$var wire 1 M _037_ $end
$var wire 1 N _038_ $end
$var wire 1 O _039_ $end
$var wire 1 P _040_ $end
$var wire 1 Q _041_ $end
$var wire 1 R _042_ $end
$var wire 1 S _043_ $end
$var wire 1 T _044_ $end
$var wire 1 U _045_ $end
$var wire 1 V _046_ $end
$var wire 1 W _047_ $end
$var wire 1 X _048_ $end
$var wire 1 Y _049_ $end
$var wire 1 Z _050_ $end
$var wire 1 [ _051_ $end
$var wire 8 \ a [7:0] $end
$var wire 1 * add_carry $end
$var wire 8 ] b [7:0] $end
$var wire 1 - clk $end
$var wire 3 ^ op [2:0] $end
$var wire 1 $ result_is_zero $end
$var wire 1 / rst_n $end
$var wire 8 _ xor_result [7:0] $end
$var wire 8 ` sub_result [7:0] $end
$var wire 9 a sub_full [8:0] $end
$var wire 8 b selected_result [7:0] $end
$var wire 8 c or_result [7:0] $end
$var wire 8 d and_result [7:0] $end
$var wire 8 e add_result [7:0] $end
$var wire 9 f add_full [8:0] $end
$var wire 8 g _055_ [7:0] $end
$var wire 8 h _054_ [7:0] $end
$var wire 8 i _053_ [7:0] $end
$var wire 8 j _052_ [7:0] $end
$var wire 9 k _020_ [8:0] $end
$var wire 9 l _019_ [8:0] $end
$var wire 9 m _018_ [8:0] $end
$var wire 9 n _017_ [8:0] $end
$var wire 9 o _016_ [8:0] $end
$var wire 2 p _009_ [1:0] $end
$var wire 4 q _008_ [3:0] $end
$var wire 1 r _000_ $end
$var reg 1 ' carry $end
$var reg 8 s result [7:0] $end
$var reg 1 ! zero $end
$upscope $end
$upscope $end
$enddefinitions $end
$comment Show the parameter values. $end
$dumpall
$end
#0
$dumpvars
b0 s
0r
b0 q
b0 p
b0 o
b111111111 n
bz1111111 m
b111111111 l
b0z0000000 k
b0 j
b0 i
b0 h
b0 g
b0 f
b0 e
b0 d
b0 c
b0 b
bz00000000 a
b0 `
b0 _
b0 ^
b0 ]
b0 \
0[
0Z
1Y
1X
1W
1V
1U
1T
1S
0R
0Q
1P
0O
0N
0M
0L
0K
0J
0I
0H
0G
0F
0E
0D
0C
0B
0A
0@
0?
0>
0=
1<
1;
1:
19
08
07
06
15
14
13
12
11
10
0/
b0 .
0-
b0 ,
b0 +
0*
b0 )
b0 (
0'
b0 &
b0 %
1$
b0 #
b0 "
0!
$end
#5000
1-
#10000
0-
#15000
1-
#20000
0-
1/
#25000
1!
1-
#30000
0$
17
b1 p
b10 q
bz1111101 m
b1000 b
1I
0P
b1000 )
b1000 e
b111 o
b10 #
b10 `
b1000 f
bz00000010 a
0S
1Z
1=
0W
0T
1Q
b111111100 n
b111 &
b111 c
b110 "
b110 _
b1 (
b1 d
b111111001 l
b0z0000100 k
0-
b11 ,
b11 ]
b101 +
b101 \
#35000
b1000 %
b1000 s
0!
1-
#40000
1$
07
b0 p
1K
b0 q
1r
1*
1J
1H
1C
b0 b
b11111111 o
b0 )
b0 e
bz1111111 m
b11111110 #
b11111110 `
b100000000 f
bz11111110 a
1A
1G
0V
1D
1E
1F
0Y
0X
0U
0Q
0P
1[
b111111110 n
b11111111 &
b11111111 c
b11111110 "
b11111110 _
b100000001 l
b0z1111110 k
0-
b1 ,
b1 ]
b11111111 +
b11111111 \
#45000
1'
1!
b0 %
b0 s
1-
#50000
0$
17
b10 p
b1000 q
b1111111 o
b10000000 b
0r
b10000000 )
b10000000 e
0*
b1111110 #
b1111110 `
0C
b10000000 f
bz01111110 a
0G
0F
b1111111 &
b1111111 c
b1111110 "
b1111110 _
b110000001 l
0-
b1111111 +
b1111111 \
#55000
b10000000 %
b10000000 s
0!
0'
1-
#60000
0$
17
b1 p
0J
0I
b11 q
b0 o
b1011 #
b1011 `
b10101 f
bz00001011 a
bz1110000 m
b1011 j
0A
0H
0S
b1011 b
0D
0E
0K
b10101 )
b10101 e
0=
1Y
0W
0T
1R
0P
1[
0Z
09
b111111010 n
b10101 &
b10101 c
b10101 "
b10101 _
b0 (
b0 d
b111101010 l
b0z0010000 k
03
18
01
16
0-
b1 .
b1 ^
b101 ,
b101 ]
b10000 +
b10000 \
#65000
b1011 %
b1011 s
1-
#70000
b11 p
b1111 q
b11110101 b
b11110101 j
0Y
1Z
1Q
1P
b11110101 #
b11110101 `
bz11110101 a
bz0001111 m
0[
0U
0T
0R
b111101111 n
b111101010 l
b0z0000101 k
0-
b10000 ,
b10000 ]
b101 +
b101 \
#75000
b11110101 %
b11110101 s
1-
#80000
1$
07
b0 p
b0 q
b0 b
b11111111 )
b11111111 e
b1010101 #
b1010101 `
b11111111 f
bz01010101 a
bz0101010 m
1G
b0 j
1D
1E
1F
0W
0P
1[
0Q
0:
b110101010 n
b11111111 &
b11111111 c
b11111111 "
b11111111 _
b100000000 l
b0z0101010 k
04
19
11
02
13
0-
b10 .
b10 ^
b1010101 ,
b1010101 ]
b10101010 +
b10101010 \
#85000
1!
b0 %
b0 s
1-
#90000
0$
17
b1 p
b11 q
1K
b1111 b
1*
b1111 j
1S
1J
1H
1C
0Z
1T
1P
b11110000 #
b11110000 `
b0z1110000 k
b100001110 f
b11111111 o
b1111 i
bz1111111 m
bz11110000 a
0D
b1110 )
b1110 e
1L
0Y
0X
1W
b111110000 n
b11110000 "
b11110000 _
b1111 (
b1111 d
b100001111 l
0-
b1111 ,
b1111 ]
b11111111 +
b11111111 \
#95000
b1111 %
b1111 s
0!
1-
#100000
0$
17
b11 p
b1111 q
0K
b11111111 b
0*
0J
0H
0C
b11111111 j
1Z
0P
b1010101 #
b1010101 `
b11111111 f
b0 o
bz01010101 a
bz0101010 m
b11111111 h
0A
0S
b11111111 i
1D
0I
b11111111 )
b11111111 e
0L
0Y
0X
0W
0T
0;
b110101010 n
b11111111 "
b11111111 _
b0 (
b0 d
b100000000 l
b0z0101010 k
05
1:
01
14
0-
b11 .
b11 ^
b1010101 ,
b1010101 ]
b10101010 +
b10101010 \
#105000
b11111111 %
b11111111 s
1-
#110000
1$
07
b0 p
b0 q
b0 b
1P
b0 j
b0 #
b0 `
bz1111111 m
bz00000000 a
1V
1S
0[
0Z
1Y
1X
1W
1U
1T
b0 i
b0z0000000 k
b111111111 l
b101010100 f
b10101010 o
1*
0G
1O
b0 g
0D
0E
0F
b1010100 )
b1010100 e
1L
1M
1N
b0 h
b101010101 n
b10101010 &
b10101010 c
b0 "
b0 _
b10101010 (
b10101010 d
15
0<
00
11
12
13
14
1;
06
0-
b100 .
b100 ^
b10101010 ,
b10101010 ]
#115000
b0 %
b0 s
1!
1-
#120000
0$
17
b11 p
b1111 q
b11111111 b
b11111111 j
b11111111 i
b1010101 #
b1010101 `
bz0101010 m
bz01010101 a
b11111111 h
0V
0S
1[
1Z
0Y
0X
0W
0U
0T
0P
b0z0101010 k
b100000000 l
0C
b11111111 f
b11111111 g
b0 o
0*
0A
0H
1G
0O
1D
1E
1F
0I
0J
0K
b11111111 )
b11111111 e
0L
0M
0N
b110101010 n
b11111111 &
b11111111 c
b11111111 "
b11111111 _
b0 (
b0 d
0-
b1010101 ,
b1010101 ]
#125000
0!
b11111111 %
b11111111 s
1-
#130000
1Y
1X
1V
1$
07
1W
1S
b0 j
b0 p
b0 q
b0 i
1P
b0 h
1U
1T
b0 #
b0 `
b0 f
b0 b
bz00000000 a
bz1111111 m
0G
b0 g
0D
0E
0F
b0 )
b0 e
0[
0Z
b111111111 n
b0 &
b0 c
b0 "
b0 _
b111111111 l
b0z0000000 k
1<
10
08
0-
b0 .
b0 ^
b0 ,
b0 ]
b0 +
b0 \
#135000
b0 %
b0 s
1!
1-
